jws2txt/__init__.py
jws2txt/jws2txt.py
jws2txt/helpers/__init.py
jws2txt/helpers/helpers.py
jws2txt-1.0.0.dist-info/METADATA
jws2txt-1.0.0.dist-info/WHEEL
jws2txt-1.0.0.dist-info/entry_points.txt
jws2txt-1.0.0.dist-info/licenses/LICENSE.txt
jws2txt-1.0.0.dist-info/RECORD
