Metadata-Version: 2.1
Name: jws2txt
Version: 1.0.0
Summary: A JASCO file (*.jws and *.jwb) to text file converter.
Project-URL: Homepage, https://github.com/jzftran/jws2txt
Project-URL: Bug Tracker, https://github.com/jzftran/jws2txt/issues
Author-email: Józef Tran <jozeftran@gmail.com>
License-File: LICENSE.txt
Classifier: Intended Audience :: Science/Research
Classifier: License :: OSI Approved :: MIT License
Classifier: Operating System :: OS Independent
Classifier: Programming Language :: Python :: 3
Classifier: Topic :: Scientific/Engineering :: Chemistry
Requires-Python: >=3.8
